langdetect/__init__.py
langdetect/detector.py
langdetect/detector_factory.py
langdetect/fix-ko.py
langdetect/lang_detect_exception.py
langdetect/language.py
langdetect/profiles/af
langdetect/profiles/ar
langdetect/profiles/bg
langdetect/profiles/bn
langdetect/profiles/ca
langdetect/profiles/cs
langdetect/profiles/cy
langdetect/profiles/da
langdetect/profiles/de
langdetect/profiles/el
langdetect/profiles/en
langdetect/profiles/es
langdetect/profiles/et
langdetect/profiles/fa
langdetect/profiles/fi
langdetect/profiles/fr
langdetect/profiles/gu
langdetect/profiles/he
langdetect/profiles/hi
langdetect/profiles/hr
langdetect/profiles/hu
langdetect/profiles/id
langdetect/profiles/it
langdetect/profiles/ja
langdetect/profiles/kn
langdetect/profiles/ko
langdetect/profiles/lt
langdetect/profiles/lv
langdetect/profiles/mk
langdetect/profiles/ml
langdetect/profiles/mr
langdetect/profiles/ne
langdetect/profiles/nl
langdetect/profiles/no
langdetect/profiles/pa
langdetect/profiles/pl
langdetect/profiles/pt
langdetect/profiles/ro
langdetect/profiles/ru
langdetect/profiles/sk
langdetect/profiles/sl
langdetect/profiles/so
langdetect/profiles/sq
langdetect/profiles/sv
langdetect/profiles/sw
langdetect/profiles/ta
langdetect/profiles/te
langdetect/profiles/th
langdetect/profiles/tl
langdetect/profiles/tr
langdetect/profiles/uk
langdetect/profiles/ur
langdetect/profiles/vi
langdetect/profiles/zh-cn
langdetect/profiles/zh-tw
langdetect/tests/__init__.py
langdetect/tests/test_detector.py
langdetect/tests/test_language.py
langdetect/utils/__init__.py
langdetect/utils/lang_profile.py
langdetect/utils/messages.properties
langdetect/utils/messages.py
langdetect/utils/ngram.py
langdetect/utils/unicode_block.py
langdetect_py-1.1.1.dist-info/LICENSE
langdetect_py-1.1.1.dist-info/METADATA
langdetect_py-1.1.1.dist-info/NOTICE
langdetect_py-1.1.1.dist-info/WHEEL
langdetect_py-1.1.1.dist-info/top_level.txt
langdetect_py-1.1.1.dist-info/RECORD
