Metadata-Version: 2.1
Name: langdetect-py
Version: 1.1.1
Summary: Language detection library ported from Google's language-detection.
Home-page: https://github.com/DoodleBears/langdetect
Author: DoodleBear
Author-email: yangmufeng233@gmail.com
License: Copyright 2014-2015 Michal "Mimino" Danilak
Keywords: language detection library
Platform: UNKNOWN
Classifier: Development Status :: 5 - Production/Stable
Classifier: Intended Audience :: Developers
Classifier: License :: OSI Approved :: Apache Software License
Classifier: Operating System :: OS Independent
Classifier: Programming Language :: Python :: 2
Classifier: Programming Language :: Python :: 2.6
Classifier: Programming Language :: Python :: 2.7
Classifier: Programming Language :: Python :: 3
Classifier: Programming Language :: Python :: 3.2
Classifier: Programming Language :: Python :: 3.3
License-File: LICENSE
License-File: NOTICE
Requires-Dist: six
